[{"customer_id":1,"first_name":"Florry","last_name":"Gough","email":"fgough0@wikipedia.org","phoneno":"488-690-3153","customer_address":"Apt 1182","city":"Mae Chan","postal":"57110","state":"Maharashtra","Country":"Thailand"},
{"customer_id":2,"first_name":"Lenore","last_name":"O'Neil","email":"loneil1@shinystat.com","phoneno":"766-900-7107","customer_address":"Apt 852","city":"Gorna Oryakhovitsa","postal":"5145","state":"Maharashtra","Country":"Bulgaria"},
{"customer_id":3,"first_name":"Marlene","last_name":"Bailes","email":"mbailes2@last.fm","phoneno":"294-654-5707","customer_address":"PO Box 97584","city":"Majiao","state":"Maharashtra","Country":"China"},
{"customer_id":4,"first_name":"Ashleigh","last_name":"Kensley","email":"akensley3@goodreads.com","phoneno":"570-485-2960","customer_address":"Apt 1793","city":"Aimin","state":"Maharashtra","Country":"China"},
{"customer_id":5,"first_name":"Gifford","last_name":"Oriel","email":"goriel4@discuz.net","phoneno":"531-295-2460","customer_address":"Room 831","city":"Ñuñoa","state":"Maharashtra","Country":"Peru"},
{"customer_id":6,"first_name":"Niko","last_name":"Messom","email":"nmessom5@woothemes.com","phoneno":"920-594-2132","customer_address":"Suite 13","city":"Sadov","postal":"360 01","state":"Maharashtra","Country":"Czech Republic"},
{"customer_id":7,"first_name":"Haley","last_name":"Bulgen","email":"hbulgen6@rediff.com","phoneno":"702-247-8608","customer_address":"PO Box 57976","city":"Las Vegas","postal":"89105","state":"Maharashtra","Country":"United States"},
{"customer_id":8,"first_name":"Stefania","last_name":"Hearnshaw","email":"shearnshaw7@amazonaws.com","phoneno":"193-378-1381","customer_address":"PO Box 43642","city":"Gurra e Vogël","state":"Maharashtra","Country":"Albania"},
{"customer_id":9,"first_name":"Estele","last_name":"Romera","email":"eromera8@ocn.ne.jp","phoneno":"967-287-4102","customer_address":"PO Box 26727","city":"Oujiangcha","state":"Maharashtra","Country":"China"},
{"customer_id":10,"first_name":"Heddie","last_name":"Lock","email":"hlock9@acquirethisname.com","phoneno":"333-494-1972","customer_address":"PO Box 15359","city":"Wawa","postal":"5108","state":"Maharashtra","Country":"Philippines"},
{"customer_id":11,"first_name":"Jeffrey","last_name":"Timlett","email":"jtimletta@unesco.org","phoneno":"742-301-5005","customer_address":"Apt 1726","city":"Shediac","postal":"E4P","state":"Maharashtra","Country":"Canada"},
{"customer_id":12,"first_name":"Hendrik","last_name":"Moubray","email":"hmoubrayb@nyu.edu","phoneno":"987-278-6070","customer_address":"Suite 11","city":"Xiangrong","state":"Maharashtra","Country":"China"},
{"customer_id":13,"first_name":"Karita","last_name":"Creavan","email":"kcreavanc@multiply.com","phoneno":"290-815-7682","customer_address":"Suite 19","city":"Kerva","postal":"140713","state":"Maharashtra","Country":"Russia"},
{"customer_id":14,"first_name":"Ulric","last_name":"Gullen","email":"ugullend@1und1.de","phoneno":"529-431-3569","customer_address":"Suite 65","city":"Ngozi","state":"Maharashtra","Country":"Burundi"},
{"customer_id":15,"first_name":"Ikey","last_name":"Mary","email":"imarye@chronoengine.com","phoneno":"515-526-7253","customer_address":"9th Floor","city":"Thị Trấn Tà Lùng","state":"Maharashtra","Country":"Vietnam"},
{"customer_id":16,"first_name":"Celine","last_name":"Ewells","email":"cewellsf@yandex.ru","phoneno":"176-740-1790","customer_address":"Suite 47","city":"Llauta","state":"Maharashtra","Country":"Peru"},
{"customer_id":17,"first_name":"Ebony","last_name":"Ogilvy","email":"eogilvyg@etsy.com","phoneno":"140-777-9425","customer_address":"PO Box 62165","city":"Sut-Khol’","postal":"668150","state":"Maharashtra","Country":"Russia"},
{"customer_id":18,"first_name":"Vladimir","last_name":"Stoyle","email":"vstoyleh@51.la","phoneno":"791-117-8805","customer_address":"Apt 37","city":"Sanjing","state":"Maharashtra","Country":"China"},
{"customer_id":19,"first_name":"Merwyn","last_name":"Giacopazzi","email":"mgiacopazzii@blog.com","phoneno":"506-488-9097","customer_address":"Apt 1412","city":"Tangwei","state":"Maharashtra","Country":"China"},
{"customer_id":20,"first_name":"Pepi","last_name":"Hubane","email":"phubanej@tuttocitta.it","phoneno":"177-422-2174","customer_address":"10th Floor","city":"Sayapullo","state":"Maharashtra","Country":"Peru"},
{"customer_id":21,"first_name":"Rhona","last_name":"Mushart","email":"rmushartk@youtube.com","phoneno":"374-962-2602","customer_address":"Apt 1227","city":"Arujá","postal":"07400-000","state":"Maharashtra","Country":"Brazil"},
{"customer_id":22,"first_name":"Woodman","last_name":"Tennant","email":"wtennantl@economist.com","phoneno":"754-806-0183","customer_address":"11th Floor","city":"Yuelai","state":"Maharashtra","Country":"China"},
{"customer_id":23,"first_name":"Cassy","last_name":"Winckworth","email":"cwinckworthm@wikia.com","phoneno":"140-752-4473","customer_address":"11th Floor","city":"Heping","state":"Maharashtra","Country":"China"},
{"customer_id":24,"first_name":"Patty","last_name":"Piscopello","email":"ppiscopellon@over-blog.com","phoneno":"308-345-5172","customer_address":"Room 99","city":"Pułtusk","postal":"06-102","state":"Maharashtra","Country":"Poland"},
{"customer_id":25,"first_name":"Adina","last_name":"Bricksey","email":"abrickseyo@paginegialle.it","phoneno":"993-933-7506","customer_address":"Suite 46","city":"Futtsu","postal":"293-0024","state":"Maharashtra","Country":"Japan"},
{"customer_id":26,"first_name":"Clemmie","last_name":"Pennuzzi","email":"cpennuzzip@seattletimes.com","phoneno":"515-702-5268","customer_address":"Apt 1075","city":"Rakvere","state":"Maharashtra","Country":"Estonia"},
{"customer_id":27,"first_name":"Clarine","last_name":"Barwell","email":"cbarwellq@state.tx.us","phoneno":"982-315-5774","customer_address":"16th Floor","city":"Bantian","state":"Maharashtra","Country":"China"},
{"customer_id":28,"first_name":"Kati","last_name":"Braxay","email":"kbraxayr@pcworld.com","phoneno":"172-864-3294","customer_address":"Suite 34","city":"Zarasai","postal":"32001","state":"Maharashtra","Country":"Lithuania"},
{"customer_id":29,"first_name":"Dar","last_name":"Gotobed","email":"dgotobeds@alibaba.com","phoneno":"155-337-2970","customer_address":"13th Floor","city":"Itapecerica","postal":"35550-000","state":"Maharashtra","Country":"Brazil"},
{"customer_id":30,"first_name":"Cymbre","last_name":"Youster","email":"cyoustert@dell.com","phoneno":"384-377-4458","customer_address":"Apt 1021","city":"Huqiu","state":"Maharashtra","Country":"China"},
{"customer_id":31,"first_name":"Katherine","last_name":"Georghiou","email":"kgeorghiouu@scientificamerican.com","phoneno":"443-118-9477","customer_address":"7th Floor","city":"Parreira","postal":"2140-514","state":"Maharashtra","Country":"Portugal"},
{"customer_id":32,"first_name":"Rebbecca","last_name":"Givens","email":"rgivensv@wired.com","phoneno":"403-975-2903","customer_address":"Apt 1729","city":"Gatak","state":"Maharashtra","Country":"Indonesia"},
{"customer_id":33,"first_name":"Colman","last_name":"Shillabeer","email":"cshillabeerw@cbc.ca","phoneno":"453-920-3139","customer_address":"Apt 51","city":"Lamadelaine","postal":"L-4888","state":"Maharashtra","Country":"Luxembourg"},
{"customer_id":34,"first_name":"Shepherd","last_name":"Dearsley","email":"sdearsleyx@hubpages.com","phoneno":"494-752-2664","customer_address":"Apt 1846","city":"Mbanza Congo","state":"Maharashtra","Country":"Angola"},
{"customer_id":35,"first_name":"Van","last_name":"Merrikin","email":"vmerrikiny@ehow.com","phoneno":"411-533-3746","customer_address":"Apt 1080","city":"Xiekou","state":"Maharashtra","Country":"China"},
{"customer_id":36,"first_name":"Beryl","last_name":"Turgoose","email":"bturgoosez@foxnews.com","phoneno":"271-669-3640","customer_address":"2nd Floor","city":"Manorhamilton","postal":"H16","state":"Maharashtra","Country":"Ireland"},
{"customer_id":37,"first_name":"Cate","last_name":"Bissatt","email":"cbissatt10@cdc.gov","phoneno":"753-710-4711","customer_address":"PO Box 36213","city":"Tarvasjoki","postal":"21450","state":"Maharashtra","Country":"Finland"},
{"customer_id":38,"first_name":"Estrella","last_name":"Woakes","email":"ewoakes11@hc360.com","phoneno":"966-753-0753","customer_address":"Room 583","city":"Galis","state":"Maharashtra","Country":"Indonesia"},
{"customer_id":39,"first_name":"Luke","last_name":"Bretherton","email":"lbretherton12@domainmarket.com","phoneno":"235-391-5622","customer_address":"PO Box 37430","city":"Motygino","postal":"157944","state":"Maharashtra","Country":"Russia"},
{"customer_id":40,"first_name":"Caprice","last_name":"Hawksby","email":"chawksby13@tiny.cc","phoneno":"769-923-7487","customer_address":"16th Floor","city":"Betulia","postal":"686508","state":"Maharashtra","Country":"Colombia"},
{"customer_id":41,"first_name":"Walsh","last_name":"Buller","email":"wbuller14@woothemes.com","phoneno":"980-818-4901","customer_address":"2nd Floor","city":"Selasari","state":"Maharashtra","Country":"Indonesia"},
{"customer_id":42,"first_name":"Lind","last_name":"Lucy","email":"llucy15@tiny.cc","phoneno":"658-277-8305","customer_address":"PO Box 1080","city":"Santa Rosa","postal":"67803","state":"Maharashtra","Country":"Mexico"},
{"customer_id":43,"first_name":"Mariska","last_name":"Blasio","email":"mblasio16@businessinsider.com","phoneno":"440-650-2833","customer_address":"Room 714","city":"Solna","postal":"169 30","state":"Maharashtra","Country":"Sweden"},
{"customer_id":44,"first_name":"Lacey","last_name":"Coyish","email":"lcoyish17@instagram.com","phoneno":"130-725-9785","customer_address":"Apt 935","city":"Cholet","postal":"49321 CEDEX","state":"Maharashtra","Country":"France"},
{"customer_id":45,"first_name":"Catherin","last_name":"Broadwell","email":"cbroadwell18@stumbleupon.com","phoneno":"335-884-4191","customer_address":"Room 1974","city":"Nishinomiya-hama","postal":"663-8234","state":"Maharashtra","Country":"Japan"},
{"customer_id":46,"first_name":"Nealon","last_name":"Di Franceschi","email":"ndifranceschi19@sciencedirect.com","phoneno":"380-441-9713","customer_address":"Room 1727","city":"Duas Igrejas","postal":"4580-373","state":"Maharashtra","Country":"Portugal"},
{"customer_id":47,"first_name":"Jewel","last_name":"Verdey","email":"jverdey1a@wsj.com","phoneno":"607-509-7682","customer_address":"Room 1153","city":"Elmira","postal":"14905","state":"Maharashtra","Country":"United States"},
{"customer_id":48,"first_name":"Elana","last_name":"Smeal","email":"esmeal1b@unblog.fr","phoneno":"217-764-1637","customer_address":"Apt 1874","city":"Yangkang","state":"Maharashtra","Country":"China"},
{"customer_id":49,"first_name":"Blane","last_name":"Mc Menamin","email":"bmcmenamin1c@aol.com","phoneno":"692-613-9462","customer_address":"11th Floor","city":"Paita","state":"Maharashtra","Country":"Peru"},
{"customer_id":50,"first_name":"Helsa","last_name":"Creeboe","email":"hcreeboe1d@go.com","phoneno":"905-344-7209","customer_address":"PO Box 62641","city":"Bègles","postal":"33324 CEDEX","state":"Maharashtra","Country":"France"},
{"customer_id":51,"first_name":"Lock","last_name":"Suermeier","email":"lsuermeier1e@nytimes.com","phoneno":"244-169-3363","customer_address":"Room 1285","city":"Mazongshan","state":"Maharashtra","Country":"China"},
{"customer_id":52,"first_name":"Hugh","last_name":"Caulket","email":"hcaulket1f@ftc.gov","phoneno":"111-604-3870","customer_address":"13th Floor","city":"Shedok","postal":"352560","state":"Maharashtra","Country":"Russia"},
{"customer_id":53,"first_name":"Gottfried","last_name":"Fitzsymonds","email":"gfitzsymonds1g@gov.uk","phoneno":"674-603-4857","customer_address":"Room 1929","city":"Valmiera","state":"Maharashtra","Country":"Latvia"},
{"customer_id":54,"first_name":"Case","last_name":"Westover","email":"cwestover1h@surveymonkey.com","phoneno":"518-547-7938","customer_address":"2nd Floor","city":"Castellon De La Plana/Castello De La Pla","postal":"12005","state":"Maharashtra","Country":"Spain"},
{"customer_id":55,"first_name":"Agata","last_name":"Strathdee","email":"astrathdee1i@hatena.ne.jp","phoneno":"968-429-1170","customer_address":"Apt 1793","city":"Khŭjand","state":"Maharashtra","Country":"Tajikistan"},
{"customer_id":56,"first_name":"Leyla","last_name":"Chazier","email":"lchazier1j@usnews.com","phoneno":"523-615-0843","customer_address":"Apt 1428","city":"Depok","state":"Maharashtra","Country":"Indonesia"},
{"customer_id":57,"first_name":"Kristen","last_name":"Swigg","email":"kswigg1k@quantcast.com","phoneno":"867-795-5663","customer_address":"Room 415","city":"Fulu","state":"Maharashtra","Country":"China"},
{"customer_id":58,"first_name":"Veda","last_name":"Eburne","email":"veburne1l@aboutads.info","phoneno":"777-346-9736","customer_address":"12th Floor","city":"Xiongguan","state":"Maharashtra","Country":"China"},
{"customer_id":59,"first_name":"Fabio","last_name":"Wudeland","email":"fwudeland1m@army.mil","phoneno":"866-663-6799","customer_address":"Suite 27","city":"28 de Noviembre","postal":"9407","state":"Maharashtra","Country":"Argentina"},
{"customer_id":60,"first_name":"Marlow","last_name":"Metheringham","email":"mmetheringham1n@pcworld.com","phoneno":"712-644-2297","customer_address":"Room 1054","city":"Storvreta","postal":"743 91","state":"Maharashtra","Country":"Sweden"},
{"customer_id":61,"first_name":"Ulises","last_name":"Barthelmes","email":"ubarthelmes1o@shop-pro.jp","phoneno":"497-588-6781","customer_address":"PO Box 75371","city":"Tertek","state":"Maharashtra","Country":"Indonesia"},
{"customer_id":62,"first_name":"Blake","last_name":"Hartles","email":"bhartles1p@bigcartel.com","phoneno":"783-623-6133","customer_address":"Apt 1534","city":"Salamina","postal":"477047","state":"Maharashtra","Country":"Colombia"},
{"customer_id":63,"first_name":"Liliane","last_name":"Renforth","email":"lrenforth1q@webeden.co.uk","phoneno":"724-565-6381","customer_address":"PO Box 96616","city":"Seboruco","state":"Maharashtra","Country":"Venezuela"},
{"customer_id":64,"first_name":"Nissy","last_name":"Ridoutt","email":"nridoutt1r@surveymonkey.com","phoneno":"733-745-6555","customer_address":"Room 546","city":"Mokil","state":"Maharashtra","Country":"Micronesia"},
{"customer_id":65,"first_name":"Lek","last_name":"Radclyffe","email":"lradclyffe1s@fda.gov","phoneno":"367-987-4471","customer_address":"PO Box 55806","city":"Anren","state":"Maharashtra","Country":"China"},
{"customer_id":66,"first_name":"Ewell","last_name":"Mussett","email":"emussett1t@ucoz.ru","phoneno":"664-221-3639","customer_address":"Room 647","city":"Lwengo","state":"Maharashtra","Country":"Uganda"},
{"customer_id":67,"first_name":"Arney","last_name":"Crossthwaite","email":"acrossthwaite1u@mayoclinic.com","phoneno":"814-295-9755","customer_address":"Apt 1940","city":"Fukou","state":"Maharashtra","Country":"China"},
{"customer_id":68,"first_name":"Redford","last_name":"Sivill","email":"rsivill1v@devhub.com","phoneno":"438-880-9640","customer_address":"12th Floor","city":"Cibeunying","state":"Maharashtra","Country":"Indonesia"},
{"customer_id":69,"first_name":"Callean","last_name":"Worsom","email":"cworsom1w@pcworld.com","phoneno":"539-551-8560","customer_address":"Apt 1000","city":"Pjanići","state":"Maharashtra","Country":"Bosnia and Herzegovina"},
{"customer_id":70,"first_name":"Gwyn","last_name":"Woodyer","email":"gwoodyer1x@google.com.br","phoneno":"221-496-7049","customer_address":"Apt 151","city":"‘Ayn al Bayḑā","state":"Maharashtra","Country":"Syria"},
{"customer_id":71,"first_name":"Charmane","last_name":"Dudson","email":"cdudson1y@lulu.com","phoneno":"369-143-1761","customer_address":"PO Box 36594","city":"Qingguang","state":"Maharashtra","Country":"China"},
{"customer_id":72,"first_name":"Natty","last_name":"Branche","email":"nbranche1z@dagondesign.com","phoneno":"872-903-7581","customer_address":"PO Box 34247","city":"San Buenaventura","state":"Maharashtra","Country":"Honduras"},
{"customer_id":73,"first_name":"Hal","last_name":"Gellert","email":"hgellert20@amazon.co.jp","phoneno":"206-728-0136","customer_address":"Room 1233","city":"Milwaukee","postal":"53285","state":"Maharashtra","Country":"United States"},
{"customer_id":74,"first_name":"Barbee","last_name":"Grimster","email":"bgrimster21@bandcamp.com","phoneno":"977-177-8616","customer_address":"Room 9","city":"Balayong","postal":"7213","state":"Maharashtra","Country":"Philippines"},
{"customer_id":75,"first_name":"Izabel","last_name":"Overell","email":"ioverell22@simplemachines.org","phoneno":"658-902-9215","customer_address":"Room 1902","city":"Zmiyëvka","postal":"303320","state":"Maharashtra","Country":"Russia"},
{"customer_id":76,"first_name":"Ervin","last_name":"Enderlein","email":"eenderlein23@disqus.com","phoneno":"128-757-1432","customer_address":"2nd Floor","city":"Amsterdam Noord west","postal":"1039","state":"Maharashtra","Country":"Netherlands"},
{"customer_id":77,"first_name":"Maxwell","last_name":"Samwell","email":"msamwell24@latimes.com","phoneno":"924-188-7052","customer_address":"Apt 727","city":"Zhishan","state":"Maharashtra","Country":"China"},
{"customer_id":78,"first_name":"Quintana","last_name":"Alebrooke","email":"qalebrooke25@unblog.fr","phoneno":"515-923-6131","customer_address":"19th Floor","city":"Cantuk Kidul","state":"Maharashtra","Country":"Indonesia"},
{"customer_id":79,"first_name":"Drew","last_name":"Mayhew","email":"dmayhew26@icq.com","phoneno":"175-392-7582","customer_address":"7th Floor","city":"Rzeczenica","postal":"77-304","state":"Maharashtra","Country":"Poland"},
{"customer_id":80,"first_name":"Waiter","last_name":"Nuemann","email":"wnuemann27@wordpress.org","phoneno":"202-894-5688","customer_address":"PO Box 59676","city":"Washington","postal":"20088","state":"Maharashtra","Country":"United States"},
{"customer_id":81,"first_name":"Crystal","last_name":"Doncom","email":"cdoncom28@edublogs.org","phoneno":"116-998-5100","customer_address":"Room 1582","city":"Marihatag","postal":"8306","state":"Maharashtra","Country":"Philippines"},
{"customer_id":82,"first_name":"Callie","last_name":"Pech","email":"cpech29@nasa.gov","phoneno":"750-631-3275","customer_address":"PO Box 76068","city":"Krajan","state":"Maharashtra","Country":"Indonesia"},
{"customer_id":83,"first_name":"Garfield","last_name":"Spurrior","email":"gspurrior2a@w3.org","phoneno":"323-943-3482","customer_address":"PO Box 75432","city":"Los Angeles","postal":"90076","state":"Maharashtra","Country":"United States"},
{"customer_id":84,"first_name":"Elnora","last_name":"MacIan","email":"emacian2b@google.nl","phoneno":"901-694-0765","customer_address":"8th Floor","city":"Gaspar","postal":"89110-000","state":"Maharashtra","Country":"Brazil"},
{"customer_id":85,"first_name":"Lucien","last_name":"Olenchikov","email":"lolenchikov2c@tmall.com","phoneno":"287-149-4638","customer_address":"16th Floor","city":"Shalang","state":"Maharashtra","Country":"China"},
{"customer_id":86,"first_name":"Natalya","last_name":"Willarton","email":"nwillarton2d@sakura.ne.jp","phoneno":"149-147-8330","customer_address":"Suite 16","city":"Ayia Napa","state":"Maharashtra","Country":"Cyprus"},
{"customer_id":87,"first_name":"Eugenia","last_name":"Hampshaw","email":"ehampshaw2e@vk.com","phoneno":"703-401-4312","customer_address":"PO Box 1481","city":"Lombog","postal":"6812","state":"Maharashtra","Country":"Philippines"},
{"customer_id":88,"first_name":"Amata","last_name":"Peschka","email":"apeschka2f@wiley.com","phoneno":"109-773-4482","customer_address":"6th Floor","city":"Bayan","state":"Maharashtra","Country":"Mongolia"},
{"customer_id":89,"first_name":"Sibley","last_name":"Dufoure","email":"sdufoure2g@hugedomains.com","phoneno":"315-674-1335","customer_address":"Apt 395","city":"Al Maţarīyah","state":"Maharashtra","Country":"Egypt"},
{"customer_id":90,"first_name":"Cornelius","last_name":"Sickamore","email":"csickamore2h@merriam-webster.com","phoneno":"921-342-7757","customer_address":"Suite 8","city":"Sarishābāri","postal":"2051","state":"Maharashtra","Country":"Bangladesh"},
{"customer_id":91,"first_name":"Billie","last_name":"Rasher","email":"brasher2i@pagesperso-orange.fr","phoneno":"174-964-4440","customer_address":"Suite 94","city":"Azeitão","postal":"2925-018","state":"Maharashtra","Country":"Portugal"},
{"customer_id":92,"first_name":"Horatia","last_name":"Larby","email":"hlarby2j@a8.net","phoneno":"924-398-9592","customer_address":"12th Floor","city":"Mapiripán","postal":"943057","state":"Maharashtra","Country":"Colombia"},
{"customer_id":93,"first_name":"Jacki","last_name":"Wimes","email":"jwimes2k@theguardian.com","phoneno":"933-670-4379","customer_address":"Suite 63","city":"Al Ghizlānīyah","state":"Maharashtra","Country":"Syria"},
{"customer_id":94,"first_name":"Pippo","last_name":"Prebble","email":"pprebble2l@wsj.com","phoneno":"414-766-3949","customer_address":"7th Floor","city":"Meilin","state":"Maharashtra","Country":"China"},
{"customer_id":95,"first_name":"Rozalie","last_name":"Scane","email":"rscane2m@infoseek.co.jp","phoneno":"674-673-0707","customer_address":"PO Box 94779","city":"Babice","postal":"37-754","state":"Maharashtra","Country":"Poland"},
{"customer_id":96,"first_name":"Sarah","last_name":"Harber","email":"sharber2n@nbcnews.com","phoneno":"296-961-0672","customer_address":"Apt 1920","city":"Maruoka","postal":"997-0334","state":"Maharashtra","Country":"Japan"},
{"customer_id":97,"first_name":"Marcile","last_name":"Le Port","email":"mleport2o@dmoz.org","phoneno":"583-752-1659","customer_address":"20th Floor","city":"Dasongshu","state":"Maharashtra","Country":"China"},
{"customer_id":98,"first_name":"Laureen","last_name":"Silcox","email":"lsilcox2p@friendfeed.com","phoneno":"261-823-0054","customer_address":"Room 1220","city":"São Miguel","postal":"4415-761","state":"Maharashtra","Country":"Portugal"},
{"customer_id":99,"first_name":"Caroline","last_name":"Hargie","email":"chargie2q@tmall.com","phoneno":"817-574-2021","customer_address":"PO Box 15696","city":"Paradahan","postal":"4114","state":"Maharashtra","Country":"Philippines"},
{"customer_id":100,"first_name":"Issi","last_name":"Bretelle","email":"ibretelle2r@yahoo.com","phoneno":"170-350-5067","customer_address":"PO Box 34445","city":"Umeå","postal":"905 92","state":"Maharashtra","Country":"Sweden"},
{"customer_id":101,"first_name":"Stacee","last_name":"Loddy","email":"sloddy2s@linkedin.com","phoneno":"746-866-2042","customer_address":"PO Box 60616","city":"Sukaraharja","state":"Maharashtra","Country":"Indonesia"},
{"customer_id":102,"first_name":"Hazlett","last_name":"Samson","email":"hsamson2t@deviantart.com","phoneno":"319-811-7271","customer_address":"Room 1831","city":"Los Boquerones","state":"Maharashtra","Country":"Panama"},
{"customer_id":103,"first_name":"Adora","last_name":"Rothwell","email":"arothwell2u@chronoengine.com","phoneno":"989-439-3496","customer_address":"Suite 96","city":"Saginaw","postal":"48604","state":"Maharashtra","Country":"United States"},
{"customer_id":104,"first_name":"Alecia","last_name":"Velden","email":"avelden2v@berkeley.edu","phoneno":"910-212-1493","customer_address":"14th Floor","city":"Marigot","state":"Maharashtra","Country":"Saint Martin"},
{"customer_id":105,"first_name":"Helga","last_name":"Ridger","email":"hridger2w@wiley.com","phoneno":"866-432-4355","customer_address":"Apt 1507","city":"Bridel","postal":"L-8165","state":"Maharashtra","Country":"Luxembourg"},
{"customer_id":106,"first_name":"Ainslee","last_name":"Balston","email":"abalston2x@homestead.com","phoneno":"767-925-7975","customer_address":"Room 431","city":"Kobuleti","state":"Maharashtra","Country":"Georgia"},
{"customer_id":107,"first_name":"Rozamond","last_name":"Greenough","email":"rgreenough2y@fema.gov","phoneno":"891-606-9175","customer_address":"PO Box 20436","city":"Gândara de Aquém","postal":"2425-445","state":"Maharashtra","Country":"Portugal"},
{"customer_id":108,"first_name":"Moselle","last_name":"Anster","email":"manster2z@java.com","phoneno":"277-736-0220","customer_address":"Room 940","city":"Watoona","state":"Maharashtra","Country":"Indonesia"},
{"customer_id":109,"first_name":"Vidovic","last_name":"O'Grady","email":"vogrady30@auda.org.au","phoneno":"328-578-9026","customer_address":"Suite 8","city":"Balsas","postal":"65800-000","state":"Maharashtra","Country":"Brazil"},
{"customer_id":110,"first_name":"Cher","last_name":"Warwick","email":"cwarwick31@qq.com","phoneno":"207-148-2856","customer_address":"Room 844","city":"Nongoma","postal":"3950","state":"Maharashtra","Country":"South Africa"},
{"customer_id":111,"first_name":"Joelle","last_name":"Blinde","email":"jblinde32@csmonitor.com","phoneno":"612-971-9670","customer_address":"18th Floor","city":"Arauca","postal":"810009","state":"Maharashtra","Country":"Colombia"},
{"customer_id":112,"first_name":"Chick","last_name":"Cosham","email":"ccosham33@lycos.com","phoneno":"272-887-6897","customer_address":"Suite 48","city":"Jenang Selatan","state":"Maharashtra","Country":"Indonesia"},
{"customer_id":113,"first_name":"Alex","last_name":"Dickons","email":"adickons34@craigslist.org","phoneno":"697-880-5744","customer_address":"Room 585","city":"Saint Aubin","state":"Maharashtra","Country":"Mauritius"},
{"customer_id":114,"first_name":"Caspar","last_name":"Blackler","email":"cblackler35@prnewswire.com","phoneno":"403-305-1062","customer_address":"8th Floor","city":"Al Jafr","state":"Maharashtra","Country":"Saudi Arabia"},
{"customer_id":115,"first_name":"Linzy","last_name":"Du Plantier","email":"lduplantier36@statcounter.com","phoneno":"412-195-0418","customer_address":"PO Box 21131","city":"Lanxi","state":"Maharashtra","Country":"China"},
{"customer_id":116,"first_name":"Kate","last_name":"Meert","email":"kmeert37@com.com","phoneno":"681-785-8217","customer_address":"Room 1404","city":"Chengjiao","state":"Maharashtra","Country":"China"},
{"customer_id":117,"first_name":"Kent","last_name":"Berkelay","email":"kberkelay38@moonfruit.com","phoneno":"420-851-2737","customer_address":"Suite 85","city":"Mugi","postal":"368293","state":"Maharashtra","Country":"Russia"},
{"customer_id":118,"first_name":"Bekki","last_name":"Garioch","email":"bgarioch39@virginia.edu","phoneno":"844-385-7413","customer_address":"Suite 61","city":"Swiętajno","postal":"19-411","state":"Maharashtra","Country":"Poland"},
{"customer_id":119,"first_name":"Sophronia","last_name":"Torrans","email":"storrans3a@dailymotion.com","phoneno":"302-281-0494","customer_address":"Apt 233","city":"Malapaubhara","state":"Maharashtra","Country":"Indonesia"},
{"customer_id":120,"first_name":"Gabriel","last_name":"Surfleet","email":"gsurfleet3b@wired.com","phoneno":"258-527-5540","customer_address":"Room 504","city":"Al Maţarīyah","state":"Maharashtra","Country":"Egypt"},
{"customer_id":121,"first_name":"Martica","last_name":"Annwyl","email":"mannwyl3c@tinyurl.com","phoneno":"252-735-1806","customer_address":"Apt 1457","city":"Caibiran","postal":"6548","state":"Maharashtra","Country":"Philippines"},
{"customer_id":122,"first_name":"Ruddy","last_name":"Sirett","email":"rsirett3d@wikimedia.org","phoneno":"144-140-9156","customer_address":"Suite 89","city":"Lazaro Cardenas","postal":"92933","state":"Maharashtra","Country":"Mexico"},
{"customer_id":123,"first_name":"Terri","last_name":"Lindholm","email":"tlindholm3e@slashdot.org","phoneno":"316-712-9696","customer_address":"10th Floor","city":"Xinshichang","state":"Maharashtra","Country":"China"},
{"customer_id":124,"first_name":"Gerrie","last_name":"Ducket","email":"gducket3f@phoca.cz","phoneno":"915-723-0317","customer_address":"PO Box 45047","city":"Lobanovo","postal":"614532","state":"Maharashtra","Country":"Russia"},
{"customer_id":125,"first_name":"Hermine","last_name":"Dunican","email":"hdunican3g@netscape.com","phoneno":"816-513-3919","customer_address":"Suite 62","city":"Daqingshan","state":"Maharashtra","Country":"China"},
{"customer_id":126,"first_name":"Sayer","last_name":"Dymocke","email":"sdymocke3h@go.com","phoneno":"253-835-0650","customer_address":"Room 1772","city":"Jombang","state":"Maharashtra","Country":"Indonesia"},
{"customer_id":127,"first_name":"Lanny","last_name":"Fouldes","email":"lfouldes3i@booking.com","phoneno":"236-416-9496","customer_address":"4th Floor","city":"Shimen","state":"Maharashtra","Country":"China"},
{"customer_id":128,"first_name":"Lexy","last_name":"Pamphilon","email":"lpamphilon3j@unesco.org","phoneno":"286-758-6747","customer_address":"Apt 324","city":"Balaka","state":"Maharashtra","Country":"Malawi"},
{"customer_id":129,"first_name":"Waite","last_name":"Domsalla","email":"wdomsalla3k@hao123.com","phoneno":"981-796-8975","customer_address":"Apt 449","city":"Entradas","postal":"7780-325","state":"Maharashtra","Country":"Portugal"},
{"customer_id":130,"first_name":"Patrick","last_name":"Beyn","email":"pbeyn3l@sina.com.cn","phoneno":"468-419-5983","customer_address":"Suite 90","city":"Tāfuna","postal":"96799","state":"Maharashtra","Country":"American Samoa"},
{"customer_id":131,"first_name":"Claudetta","last_name":"Roseveare","email":"croseveare3m@ted.com","phoneno":"190-843-2940","customer_address":"PO Box 22594","city":"El Monte","state":"Maharashtra","Country":"Chile"},
{"customer_id":132,"first_name":"Roman","last_name":"Roomes","email":"rroomes3n@skype.com","phoneno":"524-155-9424","customer_address":"Apt 516","city":"Babahoyo","state":"Maharashtra","Country":"Ecuador"},
{"customer_id":133,"first_name":"Cicily","last_name":"Prop","email":"cprop3o@biblegateway.com","phoneno":"522-511-7776","customer_address":"Room 1713","city":"Ridder","state":"Maharashtra","Country":"Kazakhstan"},
{"customer_id":134,"first_name":"Lisha","last_name":"Broader","email":"lbroader3p@redcross.org","phoneno":"513-424-1645","customer_address":"Room 25","city":"Châu Thành","state":"Maharashtra","Country":"Vietnam"},
{"customer_id":135,"first_name":"Dan","last_name":"Berkelay","email":"dberkelay3q@apache.org","phoneno":"337-170-1201","customer_address":"Room 801","city":"Valado dos Frades","postal":"2450-305","state":"Maharashtra","Country":"Portugal"},
{"customer_id":136,"first_name":"Myrtie","last_name":"Capelle","email":"mcapelle3r@youtu.be","phoneno":"286-303-1482","customer_address":"Suite 80","city":"Vidzy","state":"Maharashtra","Country":"Belarus"},
{"customer_id":137,"first_name":"Enid","last_name":"Shefton","email":"eshefton3s@artisteer.com","phoneno":"502-283-2725","customer_address":"PO Box 37695","city":"Schiedam postbusnummers","postal":"3109","state":"Maharashtra","Country":"Netherlands"},
{"customer_id":138,"first_name":"Fawnia","last_name":"Dumper","email":"fdumper3t@deviantart.com","phoneno":"462-221-1569","customer_address":"Room 1294","city":"Changsha","state":"Maharashtra","Country":"China"},
{"customer_id":139,"first_name":"Nelli","last_name":"Raubenheimer","email":"nraubenheimer3u@foxnews.com","phoneno":"110-234-4494","customer_address":"1st Floor","city":"Utarapasar","state":"Maharashtra","Country":"Indonesia"},
{"customer_id":140,"first_name":"Margret","last_name":"Onn","email":"monn3v@mail.ru","phoneno":"483-185-2423","customer_address":"Room 442","city":"Sidomulyo Kulon","state":"Maharashtra","Country":"Indonesia"},
{"customer_id":141,"first_name":"Ryley","last_name":"Van Halen","email":"rvanhalen3w@usgs.gov","phoneno":"607-848-7457","customer_address":"PO Box 30460","city":"Radzanów","postal":"26-807","state":"Maharashtra","Country":"Poland"},
{"customer_id":142,"first_name":"Tan","last_name":"Brookes","email":"tbrookes3x@infoseek.co.jp","phoneno":"721-924-2900","customer_address":"8th Floor","city":"Su-dong","state":"Maharashtra","Country":"South Korea"},
{"customer_id":143,"first_name":"Daniele","last_name":"Hay","email":"dhay3y@hud.gov","phoneno":"886-522-1389","customer_address":"Apt 53","city":"Wąpielsk","postal":"87-337","state":"Maharashtra","Country":"Poland"},
{"customer_id":144,"first_name":"Maryellen","last_name":"Brookton","email":"mbrookton3z@dot.gov","phoneno":"807-941-6472","customer_address":"Apt 1519","city":"Cihambali","state":"Maharashtra","Country":"Indonesia"},
{"customer_id":145,"first_name":"Bunni","last_name":"Goldson","email":"bgoldson40@wiley.com","phoneno":"760-970-6475","customer_address":"PO Box 38052","city":"Kobryn","state":"Maharashtra","Country":"Belarus"},
{"customer_id":146,"first_name":"Loralyn","last_name":"Regus","email":"lregus41@indiegogo.com","phoneno":"157-274-2214","customer_address":"Apt 1477","city":"Örebro","postal":"703 54","state":"Maharashtra","Country":"Sweden"},
{"customer_id":147,"first_name":"Pedro","last_name":"Palumbo","email":"ppalumbo42@bandcamp.com","phoneno":"156-424-8312","customer_address":"Room 1631","city":"Guyi","state":"Maharashtra","Country":"China"},
{"customer_id":148,"first_name":"Shawn","last_name":"Guilliland","email":"sguilliland43@yolasite.com","phoneno":"722-546-4581","customer_address":"PO Box 72651","city":"Sadabe","state":"Maharashtra","Country":"Madagascar"},
{"customer_id":149,"first_name":"Nat","last_name":"Kelf","email":"nkelf44@meetup.com","phoneno":"218-425-3376","customer_address":"15th Floor","city":"Cao Thượng","state":"Maharashtra","Country":"Vietnam"},
{"customer_id":150,"first_name":"Gratiana","last_name":"Brayshay","email":"gbrayshay45@parallels.com","phoneno":"138-824-5382","customer_address":"PO Box 96583","city":"Pjanići","state":"Maharashtra","Country":"Bosnia and Herzegovina"}]